bsvae/__init__.py
bsvae/hyperparam.ini
bsvae/latent/__init__.py
bsvae/latent/latent_analysis.py
bsvae/latent/latent_export.py
bsvae/main.py
bsvae/models/__init__.py
bsvae/models/decoder.py
bsvae/models/encoder.py
bsvae/models/losses.py
bsvae/models/structured.py
bsvae/models/vae.py
bsvae/networks/__init__.py
bsvae/networks/cli.py
bsvae/networks/extract_networks.py
bsvae/networks/module_extraction.py
bsvae/networks/utils.py
bsvae/ppi_cli.py
bsvae/utils/__init__.py
bsvae/utils/datasets.py
bsvae/utils/evaluate.py
bsvae/utils/helpers.py
bsvae/utils/initialization.py
bsvae/utils/mapping.py
bsvae/utils/modelIO.py
bsvae/utils/ppi.py
bsvae/utils/training.py
bsvae-0.2.1.dist-info/METADATA
bsvae-0.2.1.dist-info/WHEEL
bsvae-0.2.1.dist-info/entry_points.txt
bsvae-0.2.1.dist-info/licenses/LICENSE
bsvae-0.2.1.dist-info/RECORD
