Metadata-Version: 2.4
Name: bsvae
Version: 0.2.1
Summary: Biologically structured variational autoencoder for gene expression data with PPI priors.
License: GPL-3.0-only
License-File: LICENSE
Keywords: variational-autoencoder,structured-vae,pytorch,bioinformatics,gene-expression,protein-protein-interaction
Author: Kynon J Benjamin
Author-email: kj.benjamin90@gmail.com
Requires-Python: >=3.11,<3.14
Classifier: Intended Audience :: Science/Research
Classifier: License :: OSI Approved :: GNU General Public License v3 (GPLv3)
Classifier: Programming Language :: Python :: 3
Classifier: Programming Language :: Python :: 3.11
Classifier: Programming Language :: Python :: 3.12
Classifier: Programming Language :: Python :: 3.13
Classifier: Topic :: Scientific/Engineering :: Artificial Intelligence
Classifier: Topic :: Scientific/Engineering :: Bio-Informatics
Requires-Dist: mygene (>=3.2.2,<4.0.0)
Requires-Dist: networkx (>=3.5,<4.0)
Requires-Dist: numpy (<2.3)
Requires-Dist: pandas (>=2.3.2,<3.0.0)
Requires-Dist: pyarrow (>=19.0.0,<20.0.0)
Requires-Dist: scikit-learn (>=1.7.2,<2.0.0)
Requires-Dist: scipy (>=1.16.2,<2.0.0)
Requires-Dist: torch (>=2.8.0,<3.0.0)
Requires-Dist: tqdm (>=4.67.1,<5.0.0)
Project-URL: Bug Tracker, https://github.com/heart-gen/BSVAE/issues
Project-URL: homepage, https://bsvae.readthedocs.io/en/latest/
Project-URL: repository, https://github.com/heart-gen/BSVAE
